[{"f_names":"arcstyle_ONE-STORY","f_values":0.246807638368843},{"f_names":"gartype_Att","f_values":0.124354827115637},{"f_names":"quality_C","f_values":0.112673467143756},{"f_names":"livearea","f_values":0.099438031979338},{"f_names":"basement","f_values":0.046046589190402},{"f_names":"stories","f_values":0.043024278419572},{"f_names":"tasp","f_values":0.0408763381275},{"f_names":"sprice","f_values":0.032957123127817},{"f_names":"netprice","f_values":0.023987669110471},{"f_names":"numbdrm","f_values":0.023966028959347},{"f_names":"finbsmnt","f_values":0.023845942269179},{"f_names":"numbaths","f_values":0.021837308364482},{"f_names":"smonth","f_values":0.021373653225439}]